<?xml version="1.0" encoding="UTF-8"?>
<objects serializationModel="Studio.02.02.00">
	<object class="AudioFile" id="{0198a963-e2dc-41ed-ae6f-cf2afe4b1b69}">
		<property name="assetPath">
			<value>SFX_Turtle/SFX_Turtle_Steps/SFX_Turtle_Steps_Sand/SFX_Turtle_Steps_Sand_02.wav</value>
		</property>
		<property name="frequencyInKHz">
			<value>48</value>
		</property>
		<property name="channelCount">
			<value>1</value>
		</property>
		<property name="length">
			<value>0.12885416666666666</value>
		</property>
		<relationship name="masterAssetFolder">
			<destination>{eb198b6d-312f-4109-93f0-f1998758af77}</destination>
		</relationship>
	</object>
</objects>
